{
  "titular": "Avances alentadores en la inclusión de refugiados y migrantes en políticas de salud",
  "subtitulo": "Un paso hacia la igualdad en el acceso a la salud",
  "cuerpo": "<p>La Organización Mundial de la Salud (OMS) ha publicado un estudio que muestra un progreso significativo en la atención de la salud de los refugiados y los migrantes. El estudio revela que más de 60 países han incorporado a estos colectivos en sus leyes y políticas nacionales de salud, lo que representa dos tercios de los encuestados.</p><p>Este avance es una muestra clara del compromiso internacional para garantizar el acceso a la atención de la salud como derecho humano fundamental. Las políticas inclusivas son especialmente importantes para refugiados y migrantes, que a menudo enfrentan barreras significantes en su búsqueda por la asistencia médica.</p><p>El estudio también indica que los países con mayor compromiso en la inclusión de refugiados y migrantes en políticas de salud tienen mejores resultados en la salud pública en general. Esto sugiere que la igualdad de oportunidades en el acceso a la atención médica puede tener un impacto positivo en la salud de la población.</p><p>Por otro lado, los autores del estudio también advierten sobre las desafíos que siguen por delante. La implementación de políticas inclusivas requiere una coordinación y colaboración entre diferentes entidades gubernamentales y organizaciones no gubernamentales, además de la capacitación de los profesionales de la salud para garantizar un acceso efectivo a la atención médica para refugiados y migrantes.</p><p>Finalmente, el estudio enfatiza que la inclusión de refugiados y migrantes en políticas de salud no solo es una cuestión ética sino también económica. Los desafíos migratorios actuales se proyectan para continuar en los próximos ańos, por lo que la inclusión de estos colectivos en las políticas de salud puede ser un factor clave en el éxito o fracaso del sistema de salud nacional.</p>",
  "tags": [
    "Salud pública",
    "Refugiados y migrantes",
    "Políticas inclusivas",
    "OMS"
  ],
  "resumen_seo": "El compromiso internacional para garantizar el acceso a la atención médica como derecho humano fundamental muestra un progreso significativo en la atención de la salud de los refugiados y los migrantes. El estudio publicado por la Organización Mundial de la Salud (OMS) indica que más de 60 países han incorporado a estos colectivos en sus leyes y políticas nacionales de salud.",
  "seccion": "salud",
  "periodista": "Carmen López",
  "url_fuente": "https://www.who.int/es/news-room/26-03-2026-encouraging-progress-in-inclusive-health-policies-for-refugees-and-migrants",
  "fecha_generacion": "2026-04-04T00:51:45.429503",
  "slug": "avances-alentadores-en-la-inclusin-de-refugiados-y-202604040051"
}