{
  "titular": "El derribo de aviones estadounidenses en Irán: una provocación y respuesta a la tensión",
  "subtitulo": "Un análisis profundo sobre la reciente acción militar entre Estados Unidos y Irán",
  "cuerpo": "<p>El pasado martes, según informes de prensa, los aviones de combate estadounidenses estadounidenses fueron derribados por el ejército iraní. Esto ocurrió en el sur de Irán y ha provocado una serie de reacciones tanto de Estados Unidos como de la comunidad internacional.</p><p>Los reportes han revelado que los aviones pertenecían a las fuerzas armadas estadounidenses y estaban operando en un espacio aéreo neutro. Además, se ha informado que una de las aeronaves fue rescatada por el ejército iraní, mientras que la búsqueda continúa para encontrar al segundo.</p><p>Esta acción militar ha tenido repercusiones significativas en la región y ha aumentado las tensiones entre Estados Unidos y Irán. Experts en política y seguridad internacional han expresado su preocupación por la escalada de violencia y el riesgo de una guerra más amplia.</p><p>El gobierno estadounidense ha condenado el derribo de los aviones, mientras que Irán se ha defendido afirmando que actuó en defensa propia al haber detectado la presencia de drones hostiles en su espacio aéreo. Aunque las relaciones entre los dos países estaban mejorando lentamente después del cambio de administración, este incidente podría poner en peligro esas esperanzas.</p><p>En conclusión, el derribo de aviones estadounidenses en Irán es una provocación que ha aumentado las tensiones entre Estados Unidos y la República Islámica Irán. Aunque aún no se sabe mucho sobre los detalles del incidente, la comunidad internacional se está manteniendo alerta por el riesgo de una escalada en la violencia.</p>",
  "tags": [
    "incidente militar",
    "relaciones internacionales",
    "Irán"
  ],
  "resumen_seo": "El derribo de dos aviones estadounidenses por Irán ha aumentado las tensiones entre los dos países y la comunidad internacional se mantiene alerta. Experts han expresado su preocupación por el riesgo de una escalada en la violencia.",
  "seccion": "opinion",
  "periodista": "Isabel Mora",
  "url_fuente": "https://www.bbc.com/mundo/articles/cly91kwzp4qo?at_medium=RSS&at_campaign=rss",
  "fecha_generacion": "2026-04-04T01:08:15.373590",
  "slug": "el-derribo-de-aviones-estadounidenses-en-irn-una-p-202604040108"
}