{
  "titular": "La Privatización de Petroperú: Gobierno Balcázar ratifica el decreto y busca aval por hasta US$2.500 millones",
  "subtitulo": "Este esquema podría ser la clave para salvar a la petrolera a pesar del rechazo inicial del presidente",
  "cuerpo": "<p>El Ejecutivo ha descartado derogar el DU 010-2025, que fue impugnado por el propio mandatario meses atrás. Sin embargo, en vista de la crisis de liquidez a la que está sometida Petroperú, el gobierno ha buscado un esquema de garantías para que la petrolera acceda a financiamiento externo hasta US$2.500 millones. Esto revela una importante u-turn en las políticas del presidente Dina Boluarte, quien se opuso a la privatización en su discurso inaugural. La empresa estatal enfrenta importantes retos financieros, lo que ha llevado al gobierno a buscar una solución para evitar el colapso de la petrolera.</p><p>En los últimos meses, Petroperú ha tenido que suspender la compra de combustible para sus propias operaciones debido a la falta de fondos, lo que ha generado preocupación entre las autoridades del país. El gobierno ha seńalado que la privatización se hará con garantías para proteger los intereses del estado y los empleados, además de garantizar la continuidad de los proyectos a largo plazo de Petroperú.</p><p>Si bien la decisión ha sido bien recibida por el sector empresarial, ha generado cierta controversia entre algunos analistas y críticos que cuestionan la decisión del gobierno de volverse hacia la privatización tras reiterados compromisos de proteger la industria petrolera peruana. Además, se ha planteado la posibilidad de que la decisión pueda ser revertida en caso de que el gobierno encuentre una solución más favorable para Petroperú.</p><p>Si finalmente se lleva a cabo la privatización, tendrá un impacto importante tanto en la economía peruana como en los mercados financieros regionales. La venta de Petroperú también podría tener consecuencias políticas, especialmente si el gobierno se enfrenta a presiones internacionales para realizar una privatización rápida y eficiente.</p><p>En conclusion, la decisión del gobierno de privatizar Petroperú marca un punto importante en las políticas económicas del país. A pesar de que el proceso ha sido controvertido entre algunos analistas y críticos, es importante tener en cuenta los retos financieros a los que se enfrenta la petrolera estatal y la necesidad de buscar soluciones para evitar un posible colapso. Esto podría ser el inicio de una nueva era para Petroperú, aunque la decisión final depende del gobierno peruano y sus negociaciones con posibles inversionistas.</p>",
  "tags": [
    "privatización",
    "Petroperú",
    "gobierno",
    "economía",
    "Perú"
  ],
  "seccion": "economia",
  "periodista": "Jorge Mendoza",
  "url_fuente": "https://larepublica.pe/economia/2026/04/02/petroperu-balcazar-se-desdice-y-ratifica-decreto-de-la-privatizacion-mientras-alista-aval-por-hasta-us2500-millones-hnews-54126",
  "fecha_generacion": "2026-04-04T00:38:31.913083",
  "slug": "la-privatizacin-de-petroper-gobierno-balczar-ratif-202604040038"
}